lifter/__init__.py
lifter/auth.py
lifter/db.py
lifter/hub.py
lifter-0.1.0.dist-info/METADATA
lifter-0.1.0.dist-info/WHEEL
lifter-0.1.0.dist-info/top_level.txt
lifter-0.1.0.dist-info/RECORD
